Metadata-Version: 2.1
Name: p01.session
Version: 0.8.1
Summary: Session based on p01.memcache for Zope3
Home-page: http://pypi.python.org/pypi/p01.session
Author: Roger Ineichen, Projekt01 GmbH
Author-email: dev@projekt01.ch
License: ZPL 2.1
Keywords: z,o,p,e,3, ,z,3,c, ,p,0,1, ,s,e,s,s,i,o,n, ,m,e,m,c,a,c,h,e,d, ,m,e,m,o,r,y, ,c,a,c,h,e
Platform: UNKNOWN
Classifier: Development Status :: 4 - Beta
Classifier: Environment :: Web Environment
Classifier: Intended Audience :: Developers
Classifier: License :: OSI Approved :: Zope Public License
Classifier: Programming Language :: Python
Classifier: Natural Language :: English
Classifier: Operating System :: OS Independent
Classifier: Topic :: Internet :: WWW/HTTP
Classifier: Framework :: Zope3
Provides-Extra: test
